{
  "dashboard": {
    "news": {
      "title": "뉴스",
      "view": "보기",
      "empty": "아직 여기는 비어 있어요. 나중에 다시 확인해 주세요!"
    },
    "access": {
      "hwid": "하드웨어 ID",
      "lastChanged": "마지막 변경",
      "title": "접근 제어",
      "reset": "초기화",
      "changeable": "30일마다 변경 가능",
      "ago": "전"
    },
    "docs": {
      "title": "문서",
      "nav": {
        "setup": "설치",
        "modules": "모듈"
      },
      "description": "Opal을 최대한 활용하는 방법을 알아보세요."
    },
    "setup": {
      "commonErrors": {
        "title": "자주 발생하는 오류",
        "items": [
          {
            "title": "Java 인자 누락",
            "description": "런처 프로필에 필요한 JVM 인자가 누락되었음을 의미합니다.",
            "code": "실행 오류 (코드 없음)"
          },
          {
            "title": "호환되지 않는 런처",
            "description": "이 오류는 Java 인자가 누락되었음을 의미합니다. 호환되지 않는 런처를 사용할 때 자주 발생합니다.",
            "code": "0x5e"
          },
          {
            "title": "연결 문제",
            "description": "이 오류들은 보통 인터넷 연결이 약하거나 불안정하거나, P2P VPN(예: Radmin, Hamachi) 간섭을 의미합니다. 해당 서비스를 비활성화한 뒤 다시 시도해 주세요.",
            "code": "4e-63 / 4f-63"
          },
          {
            "title": "HWID 불일치",
            "description": "정확한 원인은 확실하지 않지만, 보통 HWID를 초기화하면 해결됩니다. 필요하다면 티켓으로 초기화를 요청할 수 있습니다.",
            "code": "G-26"
          }
        ],
        "description": "아래 오류 중 하나를 겪고 있다면 다음 해결 방법을 확인해 주세요."
      },
      "faq": {
        "title": "FAQ",
        "description": "Opal 사용에 대한 자주 묻는 질문입니다.",
        "questions": {
          "olderVersions": {
            "q": "구버전 서버에서 Opal을 어떻게 사용하나요?",
            "a": "{link}를 사용하세요."
          }
        }
      },
      "instructions": {
        "step2": {
          "title": "Opal 다운로드",
          "text": "{dashLink}에서 Opal을 다운로드한 다음, Fabric API와 함께 mods 폴더에 넣어 주세요."
        },
        "title": "설치 안내",
        "step1": {
          "title": "런처 설정",
          "text": "{prismLink}를 다운로드하고 1.21.10용 새 {fabricLink} 프로필을 만든 뒤 Fabric API 모드를 설치하세요.",
          "note": "커스텀 런처가 출시되기 전까지는 Prism 사용을 권장합니다."
        },
        "description": "단계별 설치 가이드입니다.",
        "step3": {
          "title": "JVM 인자",
          "text": "다음 JVM 인자를 실행 프로필에 추가하세요(프로필 → 편집 → 설정 → Java 인자):"
        },
        "step4": {
          "title": "실행",
          "text": "Opal을 실행하세요. Opal 계정으로 로그인하라는 안내가 표시됩니다."
        }
      },
      "title": "클라이언트 설치",
      "troubleshooting": {
        "title": "문제 해결",
        "checklist": {
          "title": "체크리스트",
          "items": [
            "설치 안내를 정확히 따라 했나요?",
            "Prism 런처를 사용 중인가요?",
            "올바른 JVM 인자가 적용되었나요?",
            "시스템 시간이 동기화되어 있나요?",
            "VPN을 비활성화했거나 위치를 변경했나요?",
            "차단 지역(HK/CN)에서 접속 중인가요?",
            "패킷 스니퍼(Wireshark)를 실행하고 있지 않나요?",
            "HWID 스푸퍼를 활성화하지 않았나요?"
          ]
        },
        "description": "도움 요청 전에 확인할 만한 일반적인 문제들입니다.",
        "knownIssues": {
          "title": "알려진 이슈",
          "items": [
            "시간 동기화가 되어 있지 않음",
            "홍콩/중국 본토에서 차단( VPN으로 EU/미국에 연결 )",
            "Modrinth 런처 미지원",
            "오류 코드 4e-63 및 4f-63은 보통 인터넷 연결이 약하거나 불안정하거나, P2P VPN(예: Radmin)이 활성화된 경우를 의미함"
          ]
        }
      },
      "mods": {
        "recommended": {
          "sodium": "Sodium(성능)",
          "accountSwitcherTooltip": "계정을 연동한 뒤 Discord에 참여하면 커스텀 버전을 받을 수 있어요",
          "accountSwitcher": "게임 내 계정 전환기",
          "badge": "추천",
          "title": "추천",
          "viafabricplus": "버전 전환기",
          "optiboxes": "커스텀 하늘"
        },
        "incompatible": {
          "title": "비호환",
          "badge": "사용 금지"
        },
        "title": "모드",
        "description": "호환 및 비호환 모드 안내입니다.",
        "required": {
          "title": "필수",
          "badge": "필수"
        },
        "unsupportedLaunchers": {
          "title": "지원하지 않는 런처",
          "badge": "미지원",
          "description": "아래 런처는 지원되지 않습니다. 공식 런처 또는 호환 가능한 대안을 사용해 주세요."
        }
      },
      "description": "아래 안내에 따라 Opal을 실행해 주세요."
    },
    "downloads": {
      "updated": "업데이트",
      "changelog": "변경 사항",
      "download": "다운로드",
      "title": "다운로드",
      "ownedSince": "보유 시작",
      "downloadOpal": "Opal 다운로드",
      "selectRelease": "버전 선택",
      "opalClient": "Opal 클라이언트"
    },
    "title": "콘솔",
    "overview": {
      "title": "개요",
      "online": "온라인",
      "userId": "사용자 ID",
      "launch": "실행",
      "launches": "실행 횟수"
    },
    "manage": "관리",
    "nav": {
      "activate": "활성화",
      "users": "사용자",
      "docs": "문서",
      "setup": "설치",
      "forums": "포럼",
      "settings": "설정",
      "overview": "개요",
      "discord": "Discord",
      "home": "홈",
      "network": "네트워크",
      "configs": "설정값",
      "changelog": "변경 사항",
      "purchase": "구매"
    },
    "launcher": {
      "opalLauncher": "Opal 런처",
      "title": "런처",
      "availableSince": "사용 가능 시작",
      "updated": "업데이트",
      "changelog": "변경 사항"
    },
    "changelog": {
      "opalLauncher": "Opal 런처",
      "opal": "Opal",
      "title": "변경 사항",
      "description": "Opal 최신 버전의 변경 내용을 확인하세요!",
      "launcherBadge": "런처",
      "noNotes": "이 릴리스에는 변경 로그가 없습니다."
    },
    "activate": {
      "errors": {
        "invalidKey": "코드가 존재하지 않거나 이미 사용되었습니다.",
        "invalidCredentials": "자격 증명이 올바르지 않습니다.",
        "failedCheckout": "결제 시작에 실패했습니다",
        "generic": "문제가 발생했습니다. 잠시 후 다시 시도해 주세요."
      },
      "migrateBold": "마이그레이션",
      "title": "라이선스 활성화",
      "tabs": {
        "migrate": "마이그레이션",
        "redeem": "교환",
        "buy": "구매"
      },
      "success": {
        "title": "축하합니다!",
        "dashboard": "대시보드로 이동",
        "description": "Opal에 대한 접근 권한이 부여되었습니다. <br />환영합니다!"
      },
      "description": "활성화 키가 있나요? 아래에 입력해 교환하세요. 기존 클라이언트 접근 권한을 이전하려면 {migrateBold}를 클릭하세요.",
      "forms": {
        "redeem": {
          "placeholder": "OPAL-XXXX-XXXX-XXXX"
        },
        "migrate": {
          "description": "이미 <strong class=\"font-medium\">Opal</strong>을 보유하고 있다면, 이 기능으로 새 시스템으로 접근 권한을 이전할 수 있습니다. 도움이 필요하면 티켓을 열어 주세요.",
          "username": "사용자명",
          "password": "비밀번호"
        },
        "continue": "계속",
        "buy": {
          "button": "결제로 이동",
          "description": "<strong class=\"font-medium\">Opal</strong>을 구매하세요. 결제가 완료되면 키가 이메일로 전송됩니다."
        }
      }
    }
  },
  "footer": {
    "copyright": "Opal × Terminus. 판권 소유.",
    "terms": "이용약관",
    "privacy": "개인정보 처리방침"
  },
  "forums": {
    "suggestions": {
      "denied": "거절됨",
      "dialog": {
        "submit": "제출",
        "titleLabel": "제목",
        "submitting": "제출 중...",
        "title": "기능 제안",
        "success": "제안이 제출되었습니다",
        "contentLabel": "설명",
        "titlePlaceholder": "짧은 제목",
        "contentPlaceholder": "제안을 설명해 주세요..."
      },
      "pending": "대기 중",
      "searchPlaceholder": "제안 검색...",
      "title": "제안",
      "approved": "승인됨",
      "empty": "필터와 일치하는 제안을 찾지 못했습니다.",
      "allStatuses": "모든 상태",
      "new": "새 제안"
    },
    "warning": "리포트를 만들기 전에 동일한 버그가 이미 보고되었는지 확인해 주세요. 중복 보고는 수정이 지연됩니다.",
    "bugs": {
      "empty": "필터와 일치하는 버그 리포트를 찾지 못했습니다.",
      "version": "버전",
      "closed": "닫힘",
      "title": "버그 리포트",
      "new": "버그 신고",
      "searchPlaceholder": "버그 검색...",
      "open": "열림",
      "invalid": "무효",
      "allStatuses": "모든 상태",
      "noItems": "아직 보고된 버그가 없습니다.",
      "dialog": {
        "submit": "리포트 제출",
        "titleLabel": "이슈 제목",
        "submitting": "제출 중...",
        "title": "버그 신고",
        "stepsLabel": "재현 단계",
        "descriptionLabel": "설명",
        "versionLabel": "클라이언트 버전",
        "descriptionPlaceholder": "무슨 일이 있었나요?",
        "titlePlaceholder": "간단 요약",
        "stepsPlaceholder": "1. ...로 이동 2. 클릭...",
        "success": "버그 리포트가 제출되었습니다"
      },
      "steps": "단계"
    },
    "nav": {
      "suggestions": "제안",
      "bugs": "버그 리포트",
      "roadmap": "로드맵",
      "changelog": "변경 사항"
    },
    "roadmap": {
      "allCategories": "전체 카테고리",
      "inProgress": "진행 중",
      "searchPlaceholder": "로드맵 검색...",
      "title": "로드맵",
      "empty": "항목 없음",
      "planned": "예정",
      "done": "완료"
    },
    "warningTitle": "알려진 버그 확인"
  },
  "settings": {
    "connections": {
      "title": "연동",
      "card": {
        "connect": "연결",
        "disconnect": "연결 해제",
        "ago": "전",
        "setup": "설정",
        "title": "연동",
        "connected": "연결됨",
        "notConnected": "연결되지 않음",
        "spotify": {
          "description": "Spotify API 제한 때문에 연동을 활성화하려면 직접 Spotify 앱을 생성해야 합니다.",
          "save": "자격 증명 저장",
          "clientId": "클라이언트 ID",
          "step3": "이 Redirect URI를 앱 설정에 추가하세요:",
          "clientSecretPlaceholder": "Spotify Client Secret",
          "step1": "{link}로 이동",
          "copied": "복사됨!",
          "clientSecret": "클라이언트 시크릿",
          "title": "Spotify 연동 설정",
          "saving": "저장 중...",
          "step2": "새 앱을 생성하세요(이름/설명은 아무거나 가능)",
          "instructions": "안내:",
          "clientIdPlaceholder": "Spotify 클라이언트 ID"
        },
        "description": "계정을 타사 서비스와 연결하여 추가 기능을 이용하세요.",
        "requiresSetup": "설정 필요",
        "connectSpotify": "Spotify 연결"
      }
    },
    "nav": {
      "account": "계정",
      "connections": "연동",
      "security": "보안"
    },
    "title": "설정",
    "account": {
      "title": "계정",
      "username": {
        "requirements": "사용자명은 1~24자여야 합니다.",
        "title": "사용자명",
        "toast": "사용자명이 변경되었습니다!",
        "description": "계정에 연결된 사용자명입니다.",
        "save": "변경 사항 저장",
        "cooldown": "{time} 후에 다시 변경할 수 있습니다."
      },
      "email": {
        "title": "이메일 주소",
        "footer": "이메일 주소는 변경할 수 없습니다.",
        "description": "계정에 연결된 이메일 주소입니다."
      }
    },
    "security": {
      "title": "보안",
      "password": {
        "save": "변경 사항 저장",
        "current": "현재 비밀번호",
        "requirements": "새 비밀번호는 6~72자여야 합니다.",
        "title": "비밀번호 변경",
        "description": "보안을 위해 다른 곳에서 사용하지 않는 강력한 비밀번호를 권장합니다.",
        "toast": "비밀번호가 변경되었습니다!",
        "new": "새 비밀번호"
      },
      "twoFactor": {
        "button": "2FA 설정 시작",
        "footer": "1Password, Google Authenticator, Authy 등 신뢰할 수 있는 인증 앱 사용을 권장합니다.",
        "enabled": "활성화됨",
        "disable": "비활성화",
        "setup": {
          "verify": "확인 및 활성화",
          "cancel": "취소",
          "manualEntry": "스캔이 안 되나요? 이 코드를 수동으로 입력하세요:",
          "title": "2단계 인증 설정",
          "verifying": "확인 중...",
          "description": "인증 앱(Google Authenticator, Authy 등)으로 QR 코드를 스캔하세요",
          "verificationCode": "인증 코드"
        },
        "title": "2단계 인증",
        "backup": {
          "warning": "이 코드를 안전한 곳에 보관하세요. 다시 표시되지 않습니다.",
          "title": "백업 코드 저장",
          "copy": "전체 코드 복사",
          "description": "인증 앱을 분실했을 때 계정에 접근하기 위해 사용할 수 있습니다. 각 코드는 1회만 사용할 수 있습니다.",
          "copied": "복사됨!",
          "confirm": "코드를 저장했습니다"
        },
        "disableDialog": {
          "password": "비밀번호",
          "title": "2단계 인증 비활성화",
          "cancel": "취소",
          "description": "확인을 위해 비밀번호를 입력하세요. 계정 보안이 낮아집니다.",
          "confirm": "2FA 비활성화",
          "disabling": "비활성화 중..."
        },
        "description": "TOTP 2단계 인증으로 계정을 보호하세요.",
        "toast": "이 기능은 아직 준비되지 않았습니다!"
      }
    }
  },
  "auth": {
    "login": {
      "signIn": "로그인",
      "password": "비밀번호",
      "signUp": "회원가입",
      "noAccount": "계정이 없나요?",
      "twoFactor": {
        "title": "2단계 인증 코드",
        "back": "뒤로",
        "hint": "인증 앱의 6자리 코드 또는 백업 코드를 입력하세요."
      },
      "title": "계정에 로그인",
      "forgotPassword": "비밀번호를 잊으셨나요?",
      "email": "이메일 주소",
      "description": "계속하려면 자격 증명을 입력하세요."
    },
    "spotify": {
      "connect": "Spotify 연결"
    },
    "authorize": {
      "title": "애플리케이션 승인",
      "deny": "거부",
      "request": "{app}이(가) 계정에 연결하려고 합니다",
      "allow": "허용"
    },
    "register": {
      "submit": "회원가입",
      "password": "비밀번호",
      "signIn": "로그인",
      "confirmPassword": "비밀번호 확인",
      "title": "계정 만들기",
      "username": "사용자명",
      "email": "이메일",
      "description": "회원가입을 위해 정보를 입력해 주세요.",
      "haveAccount": "이미 계정이 있나요?"
    }
  },
  "reseller": {
    "used": "사용됨",
    "title": "리셀러 통계",
    "description": "리셀러 접두사별 키 사용 통계를 확인하세요.",
    "available": "사용 가능",
    "total": "합계"
  },
  "banner": {
    "text": "홀리데이 세일: 12월 31일까지 코드 HOLIDAY10 사용 시 10% 할인"
  },
  "home": {
    "hero": {
      "texts": [
        {
          "before": "승리를 설계하는 선택,",
          "after": "。"
        },
        {
          "before": "너무 뛰어나서 경쟁자들이 따라 하는",
          "after": "。"
        },
        {
          "before": "오리지널. 최고. 언제나",
          "after": "。"
        },
        {
          "before": "이미",
          "after": "를 가졌다면, 왜 모조품에 만족하나요?"
        },
        {
          "before": "모방은 최고의 찬사. 탁월함은",
          "after": "。"
        }
      ],
      "brand": "Opal 클라이언트",
      "description": "최고의 경험을 위해 제작된 프리미엄 Minecraft 유틸리티(핵) 클라이언트입니다. Opal은 현재 Minecraft 1.21.10용 Fabric을 지원하며, 1.8 서버와 최신 버전 서버 모두에서 부드럽고 쾌적한 경험을 제공합니다.",
      "purchase": "구매",
      "learnMore": "자세히 보기"
    },
    "features": {
      "title": "왜 Opal인가요?",
      "subtitle": "풍부한 기능을 경험하면 다른 클라이언트로 돌아가고 싶지 않을 거예요.",
      "items": {
        "userFriendly": {
          "title": "쉬운 사용성",
          "description": "Opal은 누구나 쉽게 사용할 수 있도록 설계되었습니다. 설치만 하면 바로 사용할 수 있어요!"
        },
        "compatibility": {
          "title": "폭넓은 호환성",
          "description": "Opal은 Windows, macOS, Linux에서 호환성 테스트를 완료했습니다."
        },
        "quality": {
          "title": "프리미엄 품질",
          "description": "우리는 사용자 경험을 최우선으로 하며, 클라이언트를 가능한 한 최고로 만들기 위해 노력합니다."
        },
        "abundant": {
          "title": "풍부한 기능",
          "description": "Opal은 다양한 모듈과 폭넓은 커스터마이징 옵션을 제공합니다."
        },
        "trusted": {
          "title": "수천 명의 선택",
          "description": "수년간 클라이언트를 개발해 온 최정상급 개발자들이 Opal을 만들었습니다."
        },
        "updates": {
          "title": "지속적인 업데이트",
          "description": "새로운 기능으로 앞서갈 수 있도록 자주 업데이트를 제공합니다."
        }
      }
    },
    "cta": {
      "title": "Minecraft 경험을 한 단계 끌어올리세요 — 여기서 시작합니다。",
      "button": "지금 구매"
    },
    "media": {
      "title": "미디어",
      "subtitle": "커뮤니티가 만든 영상들을 확인해 보세요!"
    }
  },
  "manage": {
    "roadmap": {
      "descriptionLabel": "설명",
      "feature": "기능",
      "title": "로드맵",
      "addItem": "항목 추가",
      "searchPlaceholder": "로드맵 검색...",
      "editItem": "항목 편집",
      "inProgress": "진행 중",
      "categoryLabel": "카테고리",
      "toast": {
        "updated": "항목이 업데이트되었습니다",
        "created": "항목이 생성되었습니다",
        "deleted": "항목이 삭제되었습니다"
      },
      "categoryPlaceholder": "예: Client",
      "bug": "버그",
      "done": "완료",
      "statusLabel": "상태",
      "titleLabel": "제목",
      "planned": "예정",
      "table": {
        "status": "상태",
        "title": "제목",
        "empty": "항목이 없습니다",
        "type": "유형",
        "category": "카테고리",
        "actions": "작업"
      },
      "typeLabel": "유형",
      "filterStatus": "상태로 필터",
      "allStatuses": "모든 상태",
      "createItem": "항목 생성",
      "save": "저장",
      "saving": "저장 중...",
      "confirmDelete": "정말 삭제할까요?"
    },
    "bugs": {
      "filterStatus": "상태로 필터",
      "confirmClose": "이 버그 리포트를 닫을까요?",
      "closed": "닫힘",
      "title": "버그 리포트",
      "searchPlaceholder": "버그 리포트 검색...",
      "open": "열림",
      "invalid": "무효",
      "allStatuses": "모든 상태",
      "table": {
        "author": "작성자",
        "status": "상태",
        "empty": "버그 리포트가 없습니다",
        "created": "생성일",
        "version": "버전",
        "issue": "이슈",
        "actions": "작업"
      },
      "confirmInvalid": "무효로 표시할까요?",
      "confirmDelete": "정말 확실한가요? 이 버그 리포트는 영구적으로 삭제됩니다.",
      "toast": {
        "closed": "버그 리포트가 닫혔습니다",
        "invalid": "버그 리포트가 무효로 표시되었습니다",
        "deleted": "버그 리포트가 삭제되었습니다"
      }
    },
    "suggestions": {
      "denied": "거절됨",
      "confirmDelete": "정말 확실한가요? 이 제안은 영구적으로 삭제됩니다.",
      "pending": "대기 중",
      "searchPlaceholder": "제안 검색...",
      "title": "제안",
      "approved": "승인됨",
      "table": {
        "author": "작성자",
        "content": "내용",
        "status": "상태",
        "votes": "투표",
        "empty": "제안이 없습니다",
        "created": "생성일",
        "actions": "작업"
      },
      "confirmDeny": "이 제안을 거절할까요?",
      "allStatuses": "모든 상태",
      "filterStatus": "상태로 필터",
      "toast": {
        "deleted": "제안이 삭제되었습니다",
        "approved": "제안이 승인되었고 코인이 지급되었습니다",
        "denied": "제안이 거절되었습니다"
      }
    }
  },
  "network": {
    "common": {
      "confirm": "확인",
      "save": "저장",
      "unknown": "알 수 없음",
      "edit": "편집",
      "cancel": "취소",
      "close": "닫기",
      "noPermission": "이 항목에 접근할 권한이 없습니다.",
      "delete": "삭제",
      "remaining": "남음",
      "no": "아니요",
      "thisMonth": "이번 달",
      "never": "없음",
      "all": "전체",
      "yes": "예",
      "loading": "로딩 중..."
    },
    "networkSuffix": "네트워크",
    "keys": {
      "stats": "총 {total}개 • {used}개 사용됨 • {unused}개 사용 가능",
      "noKeysYet": "아직 키가 없습니다",
      "allResellers": "모든 리셀러",
      "count": "네트워크에 키 {count}개",
      "unusedOnly": "미사용만",
      "noResellersFirst": "이 네트워크에는 아직 리셀러가 없습니다. 키를 생성하려면 먼저 리셀러를 추가하세요.",
      "noMatchFilters": "필터와 일치하는 키가 없습니다.",
      "generate": {
        "submit": "키 생성",
        "result": {
          "title": "키가 생성되었습니다",
          "copyAll": "전체 키 복사",
          "description": "{count}개의 키가 생성되었습니다. 지금 복사하세요 - 다시 볼 수 없습니다.",
          "amountOwed": "미지급 금액:"
        },
        "reseller": "리셀러",
        "title": "키 생성",
        "count": "키 개수",
        "countPlaceholder": "1-100",
        "success": "{count}개의 키 생성 - ${usd} ({local} {currency})",
        "description": "리셀러용 키를 생성합니다. 키 1개당 ${price}가 청구됩니다.",
        "resellerPlaceholder": "리셀러 선택",
        "error": "키 생성에 실패했습니다"
      },
      "copyUnusedKeys": "미사용 키 복사",
      "title": "키",
      "countPlural": "네트워크에 키 {count}개",
      "usedOnly": "사용됨만",
      "table": {
        "status": "상태",
        "redeemed": "사용 시각",
        "unused": "미사용",
        "reseller": "리셀러",
        "media": "미디어",
        "created": "생성일",
        "key": "키",
        "used": "사용됨"
      },
      "generateKeys": "키 생성",
      "copy": {
        "single": "키가 클립보드에 복사되었습니다",
        "multiple": "{count}개의 키가 클립보드에 복사되었습니다",
        "noUnused": "복사할 미사용 키가 없습니다"
      },
      "allKeys": "전체 키",
      "pagination": {
        "previous": "이전",
        "next": "다음",
        "page": "{total}페이지 중 {current}페이지"
      }
    },
    "title": "네트워크",
    "media": {
      "noMediaYet": "미디어 계정을 찾을 수 없습니다.",
      "actions": {
        "delete": "삭제",
        "generateKey": "키 생성",
        "edit": "편집"
      },
      "count": "네트워크에 미디어 계정 {count}개",
      "noPermission": "미디어 계정을 관리할 권한이 없습니다.",
      "title": "미디어",
      "countPlural": "네트워크에 미디어 계정 {count}개",
      "delete": {
        "confirm": "미디어 계정 \"{name}\"을(를) 삭제할까요?",
        "success": "미디어 계정이 삭제되었습니다",
        "error": "미디어 계정 삭제에 실패했습니다"
      },
      "generateKey": {
        "confirm": "\"{name}\"용 키를 생성할까요?",
        "success": "키가 생성되어 복사되었습니다: {code}",
        "error": "키 생성에 실패했습니다"
      },
      "table": {
        "status": "상태",
        "active": "활성",
        "platform": "플랫폼",
        "key": "키",
        "added": "추가됨",
        "inactive": "비활성",
        "name": "이름",
        "noKey": "키 없음"
      },
      "addMedia": "미디어 추가",
      "monthlyUsage": "이번 달 {used}/{limit}개 사용 • {remaining}개 남음",
      "create": {
        "description": "네트워크의 미디어 프로그램에 크리에이터를 추가하세요.",
        "platformPlaceholder": "플랫폼 선택",
        "limitReached": "월 한도에 도달했습니다",
        "submit": "미디어 추가",
        "notesPlaceholder": "연락처, 콘텐츠 방향 등",
        "platformUrlPlaceholder": "https://youtube.com/@channel",
        "successWithKey": "미디어 계정이 생성되었습니다! 키 복사됨: {key}",
        "error": "미디어 계정 생성에 실패했습니다",
        "title": "미디어 계정 추가",
        "notes": "메모",
        "platform": "플랫폼",
        "generateKey": "키 생성",
        "platformUrl": "채널/프로필 URL",
        "keysRemaining": "이번 달 남은 미디어 키 {count}개",
        "success": "미디어 계정이 생성되었습니다",
        "name": "이름",
        "namePlaceholder": "크리에이터 이름 또는 채널"
      },
      "edit": {
        "success": "미디어 계정이 업데이트되었습니다",
        "title": "미디어 계정 편집",
        "submit": "변경 사항 저장",
        "description": "미디어 계정 정보를 업데이트합니다.",
        "error": "미디어 계정 업데이트에 실패했습니다"
      }
    },
    "nav": {
      "users": "사용자",
      "resellers": "리셀러",
      "keys": "키",
      "payments": "결제",
      "overview": "개요",
      "media": "미디어"
    },
    "payments": {
      "overpaid": "크레딧 잔액",
      "balanceOwed": "미지급 잔액",
      "paymentsReceived": "수령한 결제",
      "noPermission": "결제를 볼 권한이 없습니다.",
      "payments": "결제",
      "totalCharges": "총 청구액",
      "youOwe": "미지급 잔액",
      "title": "결제",
      "perKeyGenerated": "키 생성당",
      "table": {
        "charge": "청구",
        "keys": "키",
        "usdAmount": "USD 금액",
        "generatedBy": "생성자",
        "payment": "결제",
        "date": "날짜",
        "localAmount": "현지 금액",
        "type": "유형"
      },
      "keysGenerated": "키 생성됨",
      "keyPrice": "키 가격",
      "settled": "전액 정산됨",
      "noPaymentsYet": "아직 결제 기록이 없습니다. 키 생성 시 기록이 생성됩니다."
    },
    "overview": {
      "totalKeysGenerated": "총 생성된 키",
      "manageResellers": "리셀러 관리",
      "keyPrice": "키 가격",
      "mediaKeyPrefix": "미디어 키 접두사",
      "yourPermissions": "내 권한",
      "withKeysFromPlural": "{count}명의 리셀러에서 온 키 포함",
      "networkInfo": "네트워크 정보",
      "withKeysFrom": "{count}명의 리셀러에서 온 키 포함",
      "manageMedia": "미디어 관리",
      "resellers": "리셀러",
      "amountOwed": "미지급 금액",
      "exchangeRate": "환율",
      "noResellersYet": "이 네트워크에는 아직 리셀러가 없습니다.",
      "generateKeys": "키 생성",
      "usersInNetwork": "네트워크 사용자",
      "mediaKeysThisMonth": "이번 달 미디어 키",
      "viewUsers": "사용자 보기",
      "currency": "통화"
    },
    "users": {
      "noUsersYet": "네트워크에 아직 사용자가 없습니다.",
      "allResellers": "모든 리셀러",
      "count": "네트워크에 사용자 {count}명",
      "noResellersFirst": "이 네트워크에는 아직 리셀러가 없습니다. 먼저 리셀러를 추가한 뒤 사용자를 확인하세요.",
      "noMatchFilters": "필터와 일치하는 사용자가 없습니다.",
      "title": "사용자",
      "countPlural": "네트워크에 사용자 {count}명",
      "searchPlaceholder": "이름 또는 이메일로 검색...",
      "table": {
        "hwid": "HWID",
        "user": "사용자",
        "key": "키",
        "registered": "등록됨",
        "actions": "작업",
        "reseller": "리셀러"
      },
      "hwid": {
        "history": "HWID 기록",
        "resetSuccess": "하드웨어 ID가 성공적으로 초기화되었습니다!",
        "bound": "바인딩됨",
        "notBound": "바인딩되지 않음",
        "historyDialog": {
          "title": "HWID 기록",
          "noHistory": "HWID 변경 기록이 없습니다.",
          "description": "{name}의 하드웨어 ID 변경 기록",
          "eventSet": "HWID 설정",
          "eventReset": "HWID 초기화"
        },
        "resetError": "하드웨어 ID 초기화에 실패했습니다.",
        "resetConfirm": {
          "title": "하드웨어 ID 초기화",
          "cancel": "취소",
          "description": "{name}의 하드웨어 ID를 초기화할까요? 다음 로그인 시 다시 인증해야 합니다.",
          "confirm": "초기화"
        },
        "reset": "HWID 초기화"
      },
      "never": "없음",
      "pagination": {
        "previous": "이전",
        "next": "다음",
        "page": "{total}페이지 중 {current}페이지"
      }
    },
    "resellers": {
      "create": {
        "description": "네트워크에 새 리셀러를 추가합니다. 접두사는 키 생성에 사용됩니다.",
        "descriptionPlaceholder": "공개 리셀러 페이지에 표시될 설명...",
        "contactInfo": "연락처(선택)",
        "prefix": "키 접두사",
        "description_field": "설명(선택)",
        "namePlaceholder": "리셀러 이름",
        "storeUrlPlaceholder": "https://...",
        "contactInfoPlaceholder": "WeChat, QQ, Discord 등",
        "error": "리셀러 생성에 실패했습니다",
        "title": "리셀러 추가",
        "storeUrl": "스토어 URL(선택)",
        "success": "리셀러가 생성되었습니다",
        "prefixPlaceholder": "예: HHKW",
        "prefixHint": "2-10자의 대문자/숫자. 키 형식: PREFIX-XXXXXXXXXXXX",
        "submit": "리셀러 추가",
        "name": "이름"
      },
      "delete": {
        "confirm": "\"{name}\"을(를) 삭제할까요? 되돌릴 수 없습니다.",
        "success": "리셀러가 삭제되었습니다",
        "error": "리셀러 삭제에 실패했습니다"
      },
      "viewStore": "스토어 보기",
      "addReseller": "리셀러 추가",
      "title": "리셀러",
      "count": "네트워크에 리셀러 {count}명",
      "countPlural": "네트워크에 리셀러 {count}명",
      "noResellersYet": "아직 리셀러가 없습니다. 첫 리셀러를 추가해 키 생성을 시작하세요.",
      "table": {
        "prefix": "접두사",
        "keys": "키",
        "status": "상태",
        "reseller": "리셀러",
        "active": "활성",
        "created": "생성일",
        "inactive": "비활성",
        "users": "사용자"
      },
      "edit": {
        "success": "리셀러가 업데이트되었습니다",
        "title": "리셀러 편집",
        "submit": "변경 사항 저장",
        "description": "\"{name}\"의 정보를 업데이트합니다.",
        "error": "리셀러 업데이트에 실패했습니다"
      }
    }
  },
  "nav": {
    "home": "홈",
    "purchase": "구매",
    "discord": "Discord",
    "dashboard": "콘솔",
    "manage": "관리"
  },
  "configs": {
    "title": "공개 설정",
    "card": {
      "ago": "전",
      "edit": "편집",
      "descriptionLabel": "설명",
      "copyCommand": "로드 명령 복사",
      "clone": "개인 설정으로 복제",
      "editTitle": "{name} 편집",
      "continue": "계속",
      "publish": "게시",
      "deleteDescription": "{name} ({id}) 및 관련된 모든 데이터가 영구적으로 삭제됩니다. 이 작업은 되돌릴 수 없습니다.",
      "descriptionPlaceholder": "이 설정은 어떤 용도인가요? 공유하고 싶은 메모를 추가하세요.",
      "chooseConfig": "게시할 설정을 선택하세요...",
      "deleteTitle": "정말 확실한가요?",
      "publishTitle": "설정을 공개로 게시하세요!",
      "namePlaceholder": "{name}의 멋진 설정",
      "changesSaved": "변경 사항이 저장되었습니다!",
      "nameLabel": "이름",
      "saveChanges": "변경 사항 저장",
      "cloneTitle": "정말 확실한가요?",
      "cloneDescription": "이 설정을 개인 설정으로 복제하려고 합니다.",
      "noDescription": "설명이 없습니다",
      "publishDescription": "기존 공개 설정을 업데이트하거나 새 설정으로 게시할 수 있습니다. 게시하면 다른 사용자가 볼 수 있습니다.",
      "cancel": "취소",
      "publishNew": "새 설정으로 게시",
      "delete": "삭제",
      "copiedToast": "명령이 클립보드에 복사되었습니다!"
    }
  },
  "purchase": {
    "header": {
      "title": "버전 선택",
      "subtitle": "Opal 단품을 구매하거나 Terminus 번들을 구매해 Opal을 무료로 포함해 전체 경험을 잠금 해제하세요."
    },
    "crypto": {
      "title": "암호화폐로 결제하나요?",
      "description": "Discord에서 티켓을 열어 USDT, BTC, ETH, LTC 또는 XMR 결제를 진행하세요."
    },
    "chinaBanner": {
      "link": "리셀러 보기",
      "text": "중국에 계신가요? 공식 리셀러를 통해 구매하면 더 나은 지원과 결제 옵션을 이용할 수 있습니다."
    },
    "opal": {
      "button": "Opal 구매",
      "paymentMethods": "카드, Apple Pay, Google Pay, Klarna, CashApp",
      "price": "8.99",
      "title": "Opal 클라이언트",
      "description": "필수 Minecraft 하이브리드 유틸리티(핵) 클라이언트. 깔끔하고 가볍고 탐지 회피에 최적화되었습니다.",
      "currency": "USD",
      "features": [
        "Opal 클라이언트 (평생)",
        "향후 모든 업데이트",
        "Discord 지원 접근"
      ],
      "featuresTitle": "포함 내용"
    },
    "upgrade": {
      "title": "기존 Opal 사용자이신가요?",
      "description": "15.00 USD에 Terminus로 업그레이드하세요. 수령을 위해 티켓을 열어 주세요."
    },
    "terminus": {
      "button": "Terminus 번들 구매",
      "paymentMethods": "카드, Apple Pay, Google Pay • Ducks Services로도 구매 가능",
      "badge": "최고 가성비",
      "price": "45.00",
      "title": "Terminus: 미니게임 에디션",
      "description": "궁극의 미니게임 클라이언트. Opal 클라이언트가 평생 무료로 포함됩니다.",
      "currency": "USD",
      "features": [
        "Terminus: 미니게임 에디션 (평생)",
        "Opal 클라이언트 무료 포함 (평생)",
        "향후 모든 업데이트",
        "Discord 지원 접근",
        "우선 지원"
      ],
      "featuresTitle": "포함 내용"
    },
    "resellers": {
      "title": "공식 리셀러",
      "visit": "스토어 방문",
      "description": "신뢰할 수 있는 파트너를 통해 Opal을 구매하고 지역 결제 수단 및 지원을 받으세요.",
      "localized": {
        "title": "글로벌 결제 수단",
        "description": "위에 없는 지역 가격 또는 특정 결제 수단이 필요하신가요? 공식 리셀러가 도와드립니다."
      }
    },
    "terms": "구매 시 이용약관에 동의하는 것으로 간주됩니다. 모든 판매는 최종입니다. 평생(Lifetime)은 제품의 수명 기간을 의미합니다."
  }
}
